plotbbox/Ubuntu-Regular.ttf
plotbbox/__init__.py
plotbbox/plot.py
plotbbox-0.1.3.dist-info/LICENSE
plotbbox-0.1.3.dist-info/METADATA
plotbbox-0.1.3.dist-info/WHEEL
plotbbox-0.1.3.dist-info/top_level.txt
plotbbox-0.1.3.dist-info/RECORD
